secretsharingng/__init__.py
secretsharingng/constant.py
secretsharingng/data_validator.py
secretsharingng/polynomials.py
secretsharingng/primes.py
secretsharingng/secret_utility.py
secretsharingng/sharing.py
secretsharingng/testing.py
secretsharingng-0.2.10.dist-info/DESCRIPTION.rst
secretsharingng-0.2.10.dist-info/METADATA
secretsharingng-0.2.10.dist-info/RECORD
secretsharingng-0.2.10.dist-info/WHEEL
secretsharingng-0.2.10.dist-info/metadata.json
secretsharingng-0.2.10.dist-info/top_level.txt
